opticlust/__init__.py
opticlust/clust.py
opticlust/recommend.py
opticlust/tree.py
opticlust/utils.py
opticlust-0.5.0.dist-info/METADATA
opticlust-0.5.0.dist-info/WHEEL
opticlust-0.5.0.dist-info/licenses/LICENSE
opticlust-0.5.0.dist-info/RECORD
