Metadata-Version: 2.4
Name: opticlust
Version: 0.5.0
Summary: Single cell clustering and recommendations at a glance
Project-URL: Homepage, https://github.com/siebrenf/opticlust
Project-URL: Readme, https://github.com/siebrenf/opticlust/README.md
Author-email: Siebren Frölich <siebrenf@gmail.com>, Julian Arts <julian.armando.arts@gmail.com>
Maintainer-email: Siebren Frölich <siebrenf@gmail.com>, Julian Arts <julian.armando.arts@gmail.com>
License:                     GNU GENERAL PUBLIC LICENSE
License-File: LICENSE
Keywords: clustering,clustree,leiden,louvain,scanpy,single-cell
Requires-Python: >=3.9
Requires-Dist: igraph>=0.10
Requires-Dist: leidenalg>=0.10.2
Requires-Dist: matplotlib>=3.6
Requires-Dist: natsort
Requires-Dist: networkx>=2.7
Requires-Dist: numpy>=1.23
Requires-Dist: pygraphviz
Requires-Dist: scanpy>=1.10
Requires-Dist: scikit-learn>=1.1
Requires-Dist: tqdm
